yash_ai/__init__.py
yash_ai/__main__.py
yash_ai/console.py
yash_ai/generate.py
yash_ai-1.0.0.dist-info/LICENSE
yash_ai-1.0.0.dist-info/METADATA
yash_ai-1.0.0.dist-info/WHEEL
yash_ai-1.0.0.dist-info/entry_points.txt
yash_ai-1.0.0.dist-info/RECORD
