Metadata-Version: 2.1
Name: yash-ai
Version: 1.0.0
Summary: Just ask what shell should do for you
Home-page: https://github.com/bsnisar/shai
License: MIT
Keywords: ai,cohere,shell
Author: Bohdan Snisar
Author-email: bogdan.sns@gmail.com
Requires-Python: >=3.7.2,<4.0
Classifier: License :: OSI Approved :: MIT License
Classifier: Programming Language :: Python
Classifier: Programming Language :: Python :: 3
Classifier: Programming Language :: Python :: 3.8
Classifier: Programming Language :: Python :: 3.9
Classifier: Programming Language :: Python :: 3.10
Classifier: Programming Language :: Python :: 3.11
Requires-Dist: cohere (>=4.27,<5.0)
Requires-Dist: rich (>=11.0,<12.0)
Requires-Dist: rich-argparse (>=1.3.0,<2.0.0)
